{
  "game_id": 38,
  "total_moves": 314,
  "total_captures": 24,
  "outcome": "Checkmate",
  "final_fen": "8/8/7r/4pk2/2pb1p2/5b2/7K/8 w - - 2 154",
  "captures": [
    {
      "move_uci": "b4c5",
      "move_san": "bxc5",
      "attacker": "Pawn",
      "defender": "Pawn",
      "attacker_strength": 1,
      "attacker_component_size": 1,
      "defender_strength": 2,
      "defender_component_size": 2,
      "equality_case": false,
      "is_en_passant": false,
      "fen_before": "rnbqkbnr/p2pp2p/6p1/1pp5/1P1P1p2/6PP/P1PBPP2/RN1QKBNR w KQkq - 2 8",
      "timestamp": "2025-10-18T05:32:52.552330Z",
      "result": "attacker_removed",
      "fen_after": "rnbqkbnr/p2pp2p/6p1/1pp5/3P1p2/6PP/P1PBPP2/RN1QKBNR b KQkq - 2 8",
      "move_number": 15
    },
    {
      "move_uci": "d4c5",
      "move_san": "dxc5",
      "attacker": "Pawn",
      "defender": "Pawn",
      "attacker_strength": 1,
      "attacker_component_size": 1,
      "defender_strength": 5,
      "defender_component_size": 3,
      "equality_case": false,
      "is_en_passant": false,
      "fen_before": "r1b1qbnr/p2ppk1p/8/npp3p1/1B1P1p2/6PP/P1PQPP2/RN1K1BNR w - - 0 13",
      "timestamp": "2025-10-18T05:32:52.555885Z",
      "result": "attacker_removed",
      "fen_after": "r1b1qbnr/p2ppk1p/8/npp3p1/1B3p2/6PP/P1PQPP2/RN1K1BNR b - - 0 13",
      "move_number": 25
    },
    {
      "move_uci": "d6f4",
      "move_san": "Qxf4+",
      "attacker": "Queen",
      "defender": "Pawn",
      "attacker_strength": 12,
      "attacker_component_size": 4,
      "defender_strength": 13,
      "defender_component_size": 3,
      "equality_case": false,
      "is_en_passant": false,
      "fen_before": "r1b1qbnr/p2pp3/3Q3p/npp2kp1/1B3p2/5PPP/P1P1P3/RN1K1BNR w - - 3 16",
      "timestamp": "2025-10-18T05:32:52.558248Z",
      "result": "attacker_removed",
      "fen_after": "r1b1qbnr/p2pp3/7p/npp2kp1/1B3p2/5PPP/P1P1P3/RN1K1BNR b - - 3 16",
      "move_number": 31
    },
    {
      "move_uci": "d8e7",
      "move_san": "Bxe7",
      "attacker": "Bishop",
      "defender": "Pawn",
      "attacker_strength": 1,
      "attacker_component_size": 1,
      "defender_strength": 23,
      "defender_component_size": 6,
      "equality_case": false,
      "is_en_passant": false,
      "fen_before": "r1bB1bnr/p2ppq2/7p/1ppkP1p1/5pPP/1nP2P2/P7/RN2KBNR w - - 1 26",
      "timestamp": "2025-10-18T05:32:52.562119Z",
      "result": "attacker_removed",
      "fen_after": "r1b2bnr/p2ppq2/7p/1ppkP1p1/5pPP/1nP2P2/P7/RN2KBNR b - - 1 26",
      "move_number": 51
    },
    {
      "move_uci": "d5e5",
      "move_san": "Kxe5",
      "attacker": "King",
      "defender": "Pawn",
      "attacker_strength": 1,
      "attacker_component_size": 1,
      "defender_strength": 1,
      "defender_component_size": 1,
      "equality_case": true,
      "is_en_passant": false,
      "fen_before": "r4bnr/p2pp3/b5qp/1ppkP1p1/5pPP/NnP2P2/P7/3RKBNR b - - 5 28",
      "timestamp": "2025-10-18T05:32:52.563812Z",
      "result": "attacker_wins",
      "fen_after": "r4bnr/p2pp3/b5qp/1pp1k1p1/5pPP/NnP2P2/P7/3RKBNR w - - 0 29",
      "move_number": 56
    },
    {
      "move_uci": "h3g5",
      "move_san": "Nxg5",
      "attacker": "Knight",
      "defender": "Pawn",
      "attacker_strength": 5,
      "attacker_component_size": 3,
      "defender_strength": 22,
      "defender_component_size": 4,
      "equality_case": false,
      "is_en_passant": false,
      "fen_before": "1r3bnr/p2pp3/b6p/1pp1kqp1/1R3pPP/NnP2P1N/P5B1/4K1R1 w - - 10 34",
      "timestamp": "2025-10-18T05:32:52.566361Z",
      "result": "attacker_removed",
      "fen_after": "1r3bnr/p2pp3/b6p/1pp1kqp1/1R3pPP/NnP2P2/P5B1/4K1R1 b - - 10 34",
      "move_number": 67
    },
    {
      "move_uci": "b4f4",
      "move_san": "Rxf4",
      "attacker": "Rook",
      "defender": "Pawn",
      "attacker_strength": 12,
      "attacker_component_size": 5,
      "defender_strength": 36,
      "defender_component_size": 9,
      "equality_case": false,
      "is_en_passant": false,
      "fen_before": "2br1b1r/p2pn3/4p2p/1pp1kqp1/PR3pPP/1nP1NP2/6B1/4K1R1 w - - 1 38",
      "timestamp": "2025-10-18T05:32:52.568512Z",
      "result": "attacker_removed",
      "fen_after": "2br1b1r/p2pn3/4p2p/1pp1kqp1/P4pPP/1nP1NP2/6B1/4K1R1 b - - 1 38",
      "move_number": 75
    },
    {
      "move_uci": "g5h4",
      "move_san": "gxh4",
      "attacker": "Pawn",
      "defender": "Pawn",
      "attacker_strength": 1,
      "attacker_component_size": 1,
      "defender_strength": 2,
      "defender_component_size": 2,
      "equality_case": false,
      "is_en_passant": false,
      "fen_before": "2br1b1r/p2pn3/4p2p/1pp1kqp1/P4pPP/1nP1NP2/6B1/4K1R1 b - - 1 38",
      "timestamp": "2025-10-18T05:32:52.569470Z",
      "result": "attacker_removed",
      "fen_after": "2br1b1r/p2pn3/4p2p/1pp1kq2/P4pPP/1nP1NP2/6B1/4K1R1 w - - 1 38",
      "move_number": 76
    },
    {
      "move_uci": "h6g5",
      "move_san": "hxg5",
      "attacker": "Pawn",
      "defender": "Pawn",
      "attacker_strength": 1,
      "attacker_component_size": 1,
      "defender_strength": 2,
      "defender_component_size": 2,
      "equality_case": false,
      "is_en_passant": false,
      "fen_before": "2br1b1r/3pN3/p3p2p/np2k1PP/P1p2p2/1nP2P2/5KB1/1q4R1 b - - 2 43",
      "timestamp": "2025-10-18T05:32:52.572319Z",
      "result": "attacker_removed",
      "fen_after": "2br1b1r/3pN3/p3p3/np2k1PP/P1p2p2/1nP2P2/5KB1/1q4R1 w - - 2 43",
      "move_number": 88
    },
    {
      "move_uci": "e7g6",
      "move_san": "Nxg6+",
      "attacker": "Knight",
      "defender": "Queen",
      "attacker_strength": 5,
      "attacker_component_size": 3,
      "defender_strength": 1,
      "defender_component_size": 1,
      "equality_case": false,
      "is_en_passant": false,
      "fen_before": "2br1b1r/3pN3/p3p1q1/np2k1PP/P1p2p2/1nP2P2/4K1B1/6R1 w - - 4 44",
      "timestamp": "2025-10-18T05:32:52.573766Z",
      "result": "attacker_wins",
      "fen_after": "2br1b1r/3p4/p3p1N1/np2k1PP/P1p2p2/1nP2P2/4K1B1/6R1 b - - 0 44",
      "move_number": 91
    },
    {
      "move_uci": "g6h8",
      "move_san": "Nxh8",
      "attacker": "Knight",
      "defender": "Rook",
      "attacker_strength": 1,
      "attacker_component_size": 1,
      "defender_strength": 1,
      "defender_component_size": 1,
      "equality_case": true,
      "is_en_passant": false,
      "fen_before": "2br3r/3p4/p3p1Nb/n4kPP/Ppp2p2/1nP2P2/4K1B1/R7 w - - 0 47",
      "timestamp": "2025-10-18T05:32:52.575311Z",
      "result": "attacker_wins",
      "fen_after": "2br3N/3p4/p3p2b/n4kPP/Ppp2p2/1nP2P2/4K1B1/R7 b - - 0 47",
      "move_number": 97
    },
    {
      "move_uci": "b4c3",
      "move_san": "bxc3",
      "attacker": "Pawn",
      "defender": "Pawn",
      "attacker_strength": 5,
      "attacker_component_size": 3,
      "defender_strength": 1,
      "defender_component_size": 1,
      "equality_case": false,
      "is_en_passant": false,
      "fen_before": "2br3N/3p4/p3p2b/n4kPP/Ppp2p2/1nP2P2/4K1B1/R7 b - - 0 47",
      "timestamp": "2025-10-18T05:32:52.576109Z",
      "result": "attacker_wins",
      "fen_after": "2br3N/3p4/p3p2b/n4kPP/P1p2p2/1np2P2/4K1B1/R7 w - - 0 48",
      "move_number": 98
    },
    {
      "move_uci": "d8h8",
      "move_san": "Rxh8",
      "attacker": "Rook",
      "defender": "Knight",
      "attacker_strength": 1,
      "attacker_component_size": 1,
      "defender_strength": 1,
      "defender_component_size": 1,
      "equality_case": true,
      "is_en_passant": false,
      "fen_before": "2br3N/3p2b1/p3p3/n3k1PP/P1p2p2/1np2P2/8/1R1K3B b - - 5 50",
      "timestamp": "2025-10-18T05:32:52.577542Z",
      "result": "attacker_wins",
      "fen_after": "2b4r/3p2b1/p3p3/n3k1PP/P1p2p2/1np2P2/8/1R1K3B w - - 0 51",
      "move_number": 104
    },
    {
      "move_uci": "g7h6",
      "move_san": "Bxh6",
      "attacker": "Bishop",
      "defender": "Pawn",
      "attacker_strength": 1,
      "attacker_component_size": 1,
      "defender_strength": 1,
      "defender_component_size": 1,
      "equality_case": true,
      "is_en_passant": false,
      "fen_before": "2b4r/6b1/p2pp2P/n4kP1/P1p2p2/2p1nP2/8/R3KB2 b - - 0 58",
      "timestamp": "2025-10-18T05:32:52.580224Z",
      "result": "attacker_wins",
      "fen_after": "2b4r/8/p2pp2b/n4kP1/P1p2p2/2p1nP2/8/R3KB2 w - - 0 59",
      "move_number": 120
    },
    {
      "move_uci": "h3e6",
      "move_san": "Bxe6",
      "attacker": "Bishop",
      "defender": "Pawn",
      "attacker_strength": 1,
      "attacker_component_size": 1,
      "defender_strength": 11,
      "defender_component_size": 5,
      "equality_case": false,
      "is_en_passant": false,
      "fen_before": "4r3/3b4/p1npp1k1/P3b1P1/2p2p2/R1p1nP1B/8/4K3 w - - 13 67",
      "timestamp": "2025-10-18T05:32:52.583253Z",
      "result": "attacker_removed",
      "fen_after": "4r3/3b4/p1npp1k1/P3b1P1/2p2p2/R1p1nP2/8/4K3 b - - 13 67",
      "move_number": 137
    },
    {
      "move_uci": "g6g5",
      "move_san": "Kxg5",
      "attacker": "King",
      "defender": "Pawn",
      "attacker_strength": 1,
      "attacker_component_size": 1,
      "defender_strength": 1,
      "defender_component_size": 1,
      "equality_case": true,
      "is_en_passant": false,
      "fen_before": "4r3/n2b4/p2pp1k1/P3b1P1/2p2p2/R1p1nP2/4K3/8 b - - 15 68",
      "timestamp": "2025-10-18T05:32:52.584460Z",
      "result": "attacker_wins",
      "fen_after": "4r3/n2b4/p2pp3/P3b1k1/2p2p2/R1p1nP2/4K3/8 w - - 0 69",
      "move_number": 140
    },
    {
      "move_uci": "a6b5",
      "move_san": "axb5",
      "attacker": "Pawn",
      "defender": "Rook",
      "attacker_strength": 1,
      "attacker_component_size": 1,
      "defender_strength": 7,
      "defender_component_size": 2,
      "equality_case": false,
      "is_en_passant": false,
      "fen_before": "4r3/n7/p1bpp3/PR2b1k1/2p2p2/2p1nP2/4K3/8 b - - 3 70",
      "timestamp": "2025-10-18T05:32:52.585555Z",
      "result": "attacker_removed",
      "fen_after": "4r3/n7/2bpp3/PR2b1k1/2p2p2/2p1nP2/4K3/8 w - - 3 70",
      "move_number": 144
    },
    {
      "move_uci": "b7a7",
      "move_san": "Rxa7",
      "attacker": "Rook",
      "defender": "Knight",
      "attacker_strength": 7,
      "attacker_component_size": 2,
      "defender_strength": 1,
      "defender_component_size": 1,
      "equality_case": false,
      "is_en_passant": false,
      "fen_before": "4r3/nR6/P1bpp2k/3n4/2pb1p2/5P2/2p1K3/8 w - - 0 74",
      "timestamp": "2025-10-18T05:32:52.587396Z",
      "result": "attacker_wins",
      "fen_after": "4r3/R7/P1bpp2k/3n4/2pb1p2/5P2/2p1K3/8 b - - 0 74",
      "move_number": 153
    },
    {
      "move_uci": "c7c6",
      "move_san": "Rxc6",
      "attacker": "Rook",
      "defender": "Bishop",
      "attacker_strength": 1,
      "attacker_component_size": 1,
      "defender_strength": 5,
      "defender_component_size": 3,
      "equality_case": false,
      "is_en_passant": false,
      "fen_before": "4r3/2R5/P1bpp1k1/8/2p2p2/4nP2/2p1K3/b7 w - - 5 77",
      "timestamp": "2025-10-18T05:32:52.588868Z",
      "result": "attacker_removed",
      "fen_after": "4r3/8/P1bpp1k1/8/2p2p2/4nP2/2p1K3/b7 b - - 5 77",
      "move_number": 159
    },
    {
      "move_uci": "g8a8",
      "move_san": "Rxa8",
      "attacker": "Rook",
      "defender": "Queen",
      "attacker_strength": 1,
      "attacker_component_size": 1,
      "defender_strength": 1,
      "defender_component_size": 1,
      "equality_case": true,
      "is_en_passant": false,
      "fen_before": "Q5r1/6k1/3pp3/1b6/2p2p2/4nP2/1bpK4/8 b - - 0 81",
      "timestamp": "2025-10-18T05:32:52.590726Z",
      "result": "attacker_wins",
      "fen_after": "r7/6k1/3pp3/1b6/2p2p2/4nP2/1bpK4/8 w - - 0 82",
      "move_number": 168
    },
    {
      "move_uci": "f1g2",
      "move_san": "Kxg2",
      "attacker": "King",
      "defender": "Knight",
      "attacker_strength": 1,
      "attacker_component_size": 1,
      "defender_strength": 1,
      "defender_component_size": 1,
      "equality_case": true,
      "is_en_passant": false,
      "fen_before": "r6k/8/3pp3/8/b1pb1p2/5P2/6n1/2b2K2 w - - 4 89",
      "timestamp": "2025-10-18T05:32:52.593171Z",
      "result": "attacker_wins",
      "fen_after": "r6k/8/3pp3/8/b1pb1p2/5P2/6K1/2b5 b - - 0 89",
      "move_number": 183
    },
    {
      "move_uci": "f1g1",
      "move_san": "Kxg1",
      "attacker": "King",
      "defender": "Bishop",
      "attacker_strength": 1,
      "attacker_component_size": 1,
      "defender_strength": 1,
      "defender_component_size": 1,
      "equality_case": true,
      "is_en_passant": false,
      "fen_before": "7k/8/3pp3/8/2p2p2/5P2/r7/b2b1Kb1 w - - 11 95",
      "timestamp": "2025-10-18T05:32:52.595145Z",
      "result": "attacker_wins",
      "fen_after": "7k/8/3pp3/8/2p2p2/5P2/r7/b2b2K1 b - - 0 95",
      "move_number": 195
    },
    {
      "move_uci": "d1f3",
      "move_san": "Bxf3",
      "attacker": "Bishop",
      "defender": "Pawn",
      "attacker_strength": 4,
      "attacker_component_size": 2,
      "defender_strength": 12,
      "defender_component_size": 2,
      "equality_case": false,
      "is_en_passant": false,
      "fen_before": "8/r7/3pp3/4b1k1/2p2p2/5P2/5K2/3b4 b - - 20 105",
      "timestamp": "2025-10-18T05:32:52.598362Z",
      "result": "attacker_removed",
      "fen_after": "8/r7/3pp3/4b1k1/2p2p2/5P2/5K2/8 w - - 20 105",
      "move_number": 216
    },
    {
      "move_uci": "d1f3",
      "move_san": "Bxf3+",
      "attacker": "Bishop",
      "defender": "Pawn",
      "attacker_strength": 16,
      "attacker_component_size": 4,
      "defender_strength": 1,
      "defender_component_size": 1,
      "equality_case": false,
      "is_en_passant": false,
      "fen_before": "8/8/2r5/4pk2/2pb1p2/5P2/8/3b3K b - - 1 152",
      "timestamp": "2025-10-18T05:32:52.611112Z",
      "result": "attacker_wins",
      "fen_after": "8/8/2r5/4pk2/2pb1p2/5b2/8/7K w - - 0 153",
      "move_number": 312
    }
  ]
}