{
  "game_id": 100,
  "total_moves": 269,
  "total_captures": 24,
  "outcome": "Stalemate",
  "final_fen": "k7/8/1Q4p1/6P1/K6P/3N2R1/8/8 b - - 9 127",
  "captures": [
    {
      "move_uci": "b4c3",
      "move_san": "Bxc3+",
      "attacker": "Bishop",
      "defender": "Pawn",
      "attacker_strength": 1,
      "attacker_component_size": 1,
      "defender_strength": 27,
      "defender_component_size": 7,
      "equality_case": false,
      "is_en_passant": false,
      "fen_before": "r1b1k1nr/pp1p1p1p/n1p3p1/4p3/1b5q/P1PPB1PB/RP2PP1P/1N1QK1NR b Kkq - 0 7",
      "timestamp": "2025-10-18T05:32:56.593096Z",
      "result": "attacker_removed",
      "fen_after": "r1b1k1nr/pp1p1p1p/n1p3p1/4p3/7q/P1PPB1PB/RP2PP1P/1N1QK1NR w Kkq - 0 7",
      "move_number": 14
    },
    {
      "move_uci": "h4h3",
      "move_san": "Qxh3",
      "attacker": "Queen",
      "defender": "Bishop",
      "attacker_strength": 1,
      "attacker_component_size": 1,
      "defender_strength": 14,
      "defender_component_size": 5,
      "equality_case": false,
      "is_en_passant": false,
      "fen_before": "r1b1k2r/pp1p1p1p/n1p2np1/4p3/1Q5q/P1PPB1PB/RP2PP1P/1N2K1NR b Kkq - 3 8",
      "timestamp": "2025-10-18T05:32:56.594840Z",
      "result": "attacker_removed",
      "fen_after": "r1b1k2r/pp1p1p1p/n1p2np1/4p3/1Q6/P1PPB1PB/RP2PP1P/1N2K1NR w Kkq - 3 8",
      "move_number": 18
    },
    {
      "move_uci": "e5d4",
      "move_san": "exd4",
      "attacker": "Pawn",
      "defender": "Pawn",
      "attacker_strength": 2,
      "attacker_component_size": 2,
      "defender_strength": 1,
      "defender_component_size": 1,
      "equality_case": false,
      "is_en_passant": false,
      "fen_before": "r1b2r1k/p4p2/npp2npp/Q2pp2B/3P1B2/P1P3PN/RP1NPP1P/4K2R b K - 0 16",
      "timestamp": "2025-10-18T05:32:56.598607Z",
      "result": "attacker_wins",
      "fen_after": "r1b2r1k/p4p2/npp2npp/Q2p3B/3p1B2/P1P3PN/RP1NPP1P/4K2R w K - 0 17",
      "move_number": 36
    },
    {
      "move_uci": "h5g6",
      "move_san": "Bxg6",
      "attacker": "Bishop",
      "defender": "Pawn",
      "attacker_strength": 1,
      "attacker_component_size": 1,
      "defender_strength": 12,
      "defender_component_size": 5,
      "equality_case": false,
      "is_en_passant": false,
      "fen_before": "r1b2r1k/p4p2/npp2npp/Q2p3B/3p1B2/P1P3PN/RP1NPP1P/4K2R w K - 0 17",
      "timestamp": "2025-10-18T05:32:56.599670Z",
      "result": "attacker_removed",
      "fen_after": "r1b2r1k/p4p2/npp2npp/Q2p4/3p1B2/P1P3PN/RP1NPP1P/4K2R b K - 0 17",
      "move_number": 37
    },
    {
      "move_uci": "d4c3",
      "move_san": "dxc3",
      "attacker": "Pawn",
      "defender": "Pawn",
      "attacker_strength": 1,
      "attacker_component_size": 1,
      "defender_strength": 1,
      "defender_component_size": 1,
      "equality_case": true,
      "is_en_passant": false,
      "fen_before": "r4r1k/p4p2/npp1bnpp/Q2p4/3p1B2/P1P3PN/1P1NPP1P/R3K2R b K - 2 18",
      "timestamp": "2025-10-18T05:32:56.601062Z",
      "result": "attacker_wins",
      "fen_after": "r4r1k/p4p2/npp1bnpp/Q2p4/5B2/P1p3PN/1P1NPP1P/R3K2R w K - 0 19",
      "move_number": 40
    },
    {
      "move_uci": "c3b2",
      "move_san": "cxb2",
      "attacker": "Pawn",
      "defender": "Pawn",
      "attacker_strength": 1,
      "attacker_component_size": 1,
      "defender_strength": 7,
      "defender_component_size": 2,
      "equality_case": false,
      "is_en_passant": false,
      "fen_before": "5r2/pr1n1p1k/Qp2bnp1/2pp2Bp/P1N1P3/2p3PN/1P3PRP/1R2K3 b - - 1 28",
      "timestamp": "2025-10-18T05:32:56.604828Z",
      "result": "attacker_removed",
      "fen_after": "5r2/pr1n1p1k/Qp2bnp1/2pp2Bp/P1N1P3/6PN/1P3PRP/1R2K3 w - - 1 28",
      "move_number": 60
    },
    {
      "move_uci": "a6a7",
      "move_san": "Qxa7",
      "attacker": "Queen",
      "defender": "Pawn",
      "attacker_strength": 1,
      "attacker_component_size": 1,
      "defender_strength": 8,
      "defender_component_size": 3,
      "equality_case": false,
      "is_en_passant": false,
      "fen_before": "2r5/pr1n1p1k/Qp2bnp1/2pp2Bp/P3P3/N5PN/1P3PRP/1R2K3 w - - 3 29",
      "timestamp": "2025-10-18T05:32:56.606122Z",
      "result": "attacker_removed",
      "fen_after": "2r5/pr1n1p1k/1p2bnp1/2pp2Bp/P3P3/N5PN/1P3PRP/1R2K3 b - - 3 29",
      "move_number": 63
    },
    {
      "move_uci": "g5f6",
      "move_san": "Bxf6",
      "attacker": "Bishop",
      "defender": "Knight",
      "attacker_strength": 1,
      "attacker_component_size": 1,
      "defender_strength": 8,
      "defender_component_size": 4,
      "equality_case": false,
      "is_en_passant": false,
      "fen_before": "7r/p1rn1p1k/1p2bnp1/2pp2Bp/P3P3/N5PN/1P3P1P/1R2K1R1 w - - 6 31",
      "timestamp": "2025-10-18T05:32:56.607412Z",
      "result": "attacker_removed",
      "fen_after": "7r/p1rn1p1k/1p2bnp1/2pp3p/P3P3/N5PN/1P3P1P/1R2K1R1 b - - 6 31",
      "move_number": 67
    },
    {
      "move_uci": "b4a5",
      "move_san": "bxa5",
      "attacker": "Pawn",
      "defender": "Pawn",
      "attacker_strength": 5,
      "attacker_component_size": 3,
      "defender_strength": 1,
      "defender_component_size": 1,
      "equality_case": false,
      "is_en_passant": false,
      "fen_before": "6n1/4rp2/1p1rb1pk/p1ppn2p/PP2PPP1/N6N/7P/3RK1R1 w - - 4 38",
      "timestamp": "2025-10-18T05:32:56.610134Z",
      "result": "attacker_wins",
      "fen_after": "6n1/4rp2/1p1rb1pk/P1ppn2p/P3PPP1/N6N/7P/3RK1R1 b - - 0 38",
      "move_number": 81
    },
    {
      "move_uci": "e5g4",
      "move_san": "Nxg4",
      "attacker": "Knight",
      "defender": "Pawn",
      "attacker_strength": 1,
      "attacker_component_size": 1,
      "defender_strength": 3,
      "defender_component_size": 3,
      "equality_case": false,
      "is_en_passant": false,
      "fen_before": "4r1n1/5p1k/1p1rb1p1/P1ppn2p/P3PPP1/7N/3K3P/1N1R2R1 b - - 4 40",
      "timestamp": "2025-10-18T05:32:56.611661Z",
      "result": "attacker_removed",
      "fen_after": "4r1n1/5p1k/1p1rb1p1/P1pp3p/P3PPP1/7N/3K3P/1N1R2R1 w - - 4 40",
      "move_number": 86
    },
    {
      "move_uci": "e6g4",
      "move_san": "Bxg4",
      "attacker": "Bishop",
      "defender": "Pawn",
      "attacker_strength": 1,
      "attacker_component_size": 1,
      "defender_strength": 3,
      "defender_component_size": 3,
      "equality_case": false,
      "is_en_passant": false,
      "fen_before": "4r1n1/5p1k/1p1rb1p1/P1pp3p/P3PPP1/7N/2K4P/1N1R2R1 b - - 5 40",
      "timestamp": "2025-10-18T05:32:56.612682Z",
      "result": "attacker_removed",
      "fen_after": "4r1n1/5p1k/1p1r2p1/P1pp3p/P3PPP1/7N/2K4P/1N1R2R1 w - - 5 40",
      "move_number": 88
    },
    {
      "move_uci": "b6a5",
      "move_san": "bxa5+",
      "attacker": "Pawn",
      "defender": "Pawn",
      "attacker_strength": 1,
      "attacker_component_size": 1,
      "defender_strength": 5,
      "defender_component_size": 3,
      "equality_case": false,
      "is_en_passant": false,
      "fen_before": "6n1/1r3pkN/1p1r2p1/P2pP2p/P1p2PP1/N7/1K5P/2R2R2 b - - 10 49",
      "timestamp": "2025-10-18T05:32:56.616222Z",
      "result": "attacker_removed",
      "fen_after": "6n1/1r3pkN/3r2p1/P2pP2p/P1p2PP1/N7/1K5P/2R2R2 w - - 10 49",
      "move_number": 108
    },
    {
      "move_uci": "f6f4",
      "move_san": "Rxf4",
      "attacker": "Rook",
      "defender": "Pawn",
      "attacker_strength": 1,
      "attacker_component_size": 1,
      "defender_strength": 2,
      "defender_component_size": 2,
      "equality_case": false,
      "is_en_passant": false,
      "fen_before": "6n1/1r3p1N/5rpk/P2pP2p/P1p2PP1/N7/K4R1P/1R6 b - - 17 52",
      "timestamp": "2025-10-18T05:32:56.617928Z",
      "result": "attacker_removed",
      "fen_after": "6n1/1r3p1N/6pk/P2pP2p/P1p2PP1/N7/K4R1P/1R6 w - - 17 52",
      "move_number": 116
    },
    {
      "move_uci": "h5g4",
      "move_san": "hxg4",
      "attacker": "Pawn",
      "defender": "Pawn",
      "attacker_strength": 1,
      "attacker_component_size": 1,
      "defender_strength": 2,
      "defender_component_size": 2,
      "equality_case": false,
      "is_en_passant": false,
      "fen_before": "6n1/1r3p1N/6pk/P2pP2p/P1p2PP1/N7/K3R2P/1R6 b - - 18 52",
      "timestamp": "2025-10-18T05:32:56.618751Z",
      "result": "attacker_removed",
      "fen_after": "6n1/1r3p1N/6pk/P2pP3/P1p2PP1/N7/K3R2P/1R6 w - - 18 52",
      "move_number": 118
    },
    {
      "move_uci": "b7h7",
      "move_san": "Rxh7",
      "attacker": "Rook",
      "defender": "Knight",
      "attacker_strength": 19,
      "attacker_component_size": 4,
      "defender_strength": 1,
      "defender_component_size": 1,
      "equality_case": false,
      "is_en_passant": false,
      "fen_before": "6n1/1r5N/5ppk/P2pP3/P1p2PPP/N3R3/K7/1R6 b - - 0 53",
      "timestamp": "2025-10-18T05:32:56.619826Z",
      "result": "attacker_wins",
      "fen_after": "6n1/7r/5ppk/P2pP3/P1p2PPP/N3R3/K7/1R6 w - - 0 54",
      "move_number": 122
    },
    {
      "move_uci": "a3c4",
      "move_san": "Nxc4",
      "attacker": "Knight",
      "defender": "Pawn",
      "attacker_strength": 1,
      "attacker_component_size": 1,
      "defender_strength": 1,
      "defender_component_size": 1,
      "equality_case": true,
      "is_en_passant": false,
      "fen_before": "8/4n2r/4Pppk/P2p4/P1p2PPP/N4R2/K7/6R1 w - - 3 57",
      "timestamp": "2025-10-18T05:32:56.621142Z",
      "result": "attacker_wins",
      "fen_after": "8/4n2r/4Pppk/P2p4/P1N2PPP/5R2/K7/6R1 b - - 0 57",
      "move_number": 129
    },
    {
      "move_uci": "g7e7",
      "move_san": "Rxe7",
      "attacker": "Rook",
      "defender": "Pawn",
      "attacker_strength": 1,
      "attacker_component_size": 1,
      "defender_strength": 1,
      "defender_component_size": 1,
      "equality_case": true,
      "is_en_passant": false,
      "fen_before": "n7/4P1r1/P5p1/P2p1pPk/5P1P/5R2/5R2/1K3N2 b - - 4 77",
      "timestamp": "2025-10-18T05:32:56.626543Z",
      "result": "attacker_wins",
      "fen_after": "n7/4r3/P5p1/P2p1pPk/5P1P/5R2/5R2/1K3N2 w - - 0 78",
      "move_number": 170
    },
    {
      "move_uci": "d2d5",
      "move_san": "Rxd5",
      "attacker": "Rook",
      "defender": "Pawn",
      "attacker_strength": 1,
      "attacker_component_size": 1,
      "defender_strength": 4,
      "defender_component_size": 2,
      "equality_case": false,
      "is_en_passant": false,
      "fen_before": "3rR3/P7/3n2p1/P2p1pP1/5P1P/7k/3R4/2K2N2 w - - 17 90",
      "timestamp": "2025-10-18T05:32:56.630540Z",
      "result": "attacker_removed",
      "fen_after": "3rR3/P7/3n2p1/P2p1pP1/5P1P/7k/8/2K2N2 b - - 17 90",
      "move_number": 195
    },
    {
      "move_uci": "g4f4",
      "move_san": "Kxf4",
      "attacker": "King",
      "defender": "Pawn",
      "attacker_strength": 12,
      "attacker_component_size": 2,
      "defender_strength": 1,
      "defender_component_size": 1,
      "equality_case": false,
      "is_en_passant": false,
      "fen_before": "Q1nr4/4R3/6p1/P2p1pP1/5PkP/8/K7/5N2 b - - 4 96",
      "timestamp": "2025-10-18T05:32:56.632866Z",
      "result": "attacker_wins",
      "fen_after": "Q1nr4/4R3/6p1/P2p1pP1/5k1P/8/K7/5N2 w - - 0 97",
      "move_number": 208
    },
    {
      "move_uci": "a8d5",
      "move_san": "Qxd5",
      "attacker": "Queen",
      "defender": "Pawn",
      "attacker_strength": 1,
      "attacker_component_size": 1,
      "defender_strength": 1,
      "defender_component_size": 1,
      "equality_case": true,
      "is_en_passant": false,
      "fen_before": "Q1nr4/4R3/6p1/P2p1pP1/5k1P/8/K7/5N2 w - - 0 97",
      "timestamp": "2025-10-18T05:32:56.633458Z",
      "result": "attacker_wins",
      "fen_after": "2nr4/4R3/6p1/P2Q1pP1/5k1P/8/K7/5N2 b - - 0 97",
      "move_number": 209
    },
    {
      "move_uci": "e7d7",
      "move_san": "Rxd7",
      "attacker": "Rook",
      "defender": "Rook",
      "attacker_strength": 1,
      "attacker_component_size": 1,
      "defender_strength": 1,
      "defender_component_size": 1,
      "equality_case": true,
      "is_en_passant": false,
      "fen_before": "2n5/3rR3/6p1/P2Q1pP1/5k1P/8/K7/5N2 w - - 1 98",
      "timestamp": "2025-10-18T05:32:56.634158Z",
      "result": "attacker_wins",
      "fen_after": "2n5/3R4/6p1/P2Q1pP1/5k1P/8/K7/5N2 b - - 0 98",
      "move_number": 211
    },
    {
      "move_uci": "d7f7",
      "move_san": "Rxf7",
      "attacker": "Rook",
      "defender": "Knight",
      "attacker_strength": 1,
      "attacker_component_size": 1,
      "defender_strength": 1,
      "defender_component_size": 1,
      "equality_case": true,
      "is_en_passant": false,
      "fen_before": "8/3R1n2/6p1/P4pP1/5k1P/K2Q4/8/5N2 w - - 11 104",
      "timestamp": "2025-10-18T05:32:56.636133Z",
      "result": "attacker_wins",
      "fen_after": "8/5R2/6p1/P4pP1/5k1P/K2Q4/8/5N2 b - - 0 104",
      "move_number": 223
    },
    {
      "move_uci": "f5f3",
      "move_san": "Rxf3",
      "attacker": "Rook",
      "defender": "Pawn",
      "attacker_strength": 9,
      "attacker_component_size": 2,
      "defender_strength": 1,
      "defender_component_size": 1,
      "equality_case": false,
      "is_en_passant": false,
      "fen_before": "8/8/P1k3p1/5RP1/6QP/K3Np2/8/8 w - - 10 112",
      "timestamp": "2025-10-18T05:32:56.638762Z",
      "result": "attacker_wins",
      "fen_after": "8/8/P1k3p1/6P1/6QP/K3NR2/8/8 b - - 0 112",
      "move_number": 239
    },
    {
      "move_uci": "b6a6",
      "move_san": "Kxa6",
      "attacker": "King",
      "defender": "Pawn",
      "attacker_strength": 1,
      "attacker_component_size": 1,
      "defender_strength": 1,
      "defender_component_size": 1,
      "equality_case": true,
      "is_en_passant": false,
      "fen_before": "8/8/Pk4p1/6P1/K6P/4N1R1/8/2Q5 b - - 20 122",
      "timestamp": "2025-10-18T05:32:56.642098Z",
      "result": "attacker_wins",
      "fen_after": "8/8/k5p1/6P1/K6P/4N1R1/8/2Q5 w - - 0 123",
      "move_number": 260
    }
  ]
}